MANIFEST.in
pyproject.toml
setup.cfg
setup.py
localstack_ext/__init__.py
localstack_ext/config.py
localstack_ext/constants.py
localstack_ext/plugins.py
localstack_ext/providers.py
localstack_ext/analytics/__init__.py
localstack_ext/analytics/aws_request_logger.py.enc
localstack_ext/analytics/plugins.py
localstack_ext/aws/__init__.py
localstack_ext/aws/api/__init__.py
localstack_ext/aws/api/amplify/__init__.py
localstack_ext/aws/api/apigatewaymanagementapi/__init__.py
localstack_ext/aws/api/apigatewayv2/__init__.py
localstack_ext/aws/api/appconfig/__init__.py
localstack_ext/aws/api/application_autoscaling/__init__.py
localstack_ext/aws/api/appsync/__init__.py
localstack_ext/aws/api/athena/__init__.py
localstack_ext/aws/api/autoscaling/__init__.py
localstack_ext/aws/api/backup/__init__.py
localstack_ext/aws/api/batch/__init__.py
localstack_ext/aws/api/ce/__init__.py
localstack_ext/aws/api/cloudfront/__init__.py
localstack_ext/aws/api/cloudtrail/__init__.py
localstack_ext/aws/api/codecommit/__init__.py
localstack_ext/aws/api/cognito_identity/__init__.py
localstack_ext/aws/api/cognito_idp/__init__.py
localstack_ext/aws/api/ecr/__init__.py
localstack_ext/aws/api/ecs/__init__.py
localstack_ext/aws/api/efs/__init__.py
localstack_ext/aws/api/eks/__init__.py
localstack_ext/aws/api/elasticache/__init__.py
localstack_ext/aws/api/elasticbeanstalk/__init__.py
localstack_ext/aws/api/elb/__init__.py
localstack_ext/aws/api/elbv2/__init__.py
localstack_ext/aws/api/emr/__init__.py
localstack_ext/aws/api/fis/__init__.py
localstack_ext/aws/api/glacier/__init__.py
localstack_ext/aws/api/glue/__init__.py
localstack_ext/aws/api/iot/__init__.py
localstack_ext/aws/api/iot_data/__init__.py
localstack_ext/aws/api/iotanalytics/__init__.py
localstack_ext/aws/api/iotwireless/__init__.py
localstack_ext/aws/api/kafka/__init__.py
localstack_ext/aws/api/kinesisanalytics/__init__.py
localstack_ext/aws/api/kinesisanalyticsv2/__init__.py
localstack_ext/aws/api/lakeformation/__init__.py
lsv2test_ext.egg-info/PKG-INFO
lsv2test_ext.egg-info/SOURCES.txt
lsv2test_ext.egg-info/dependency_links.txt
lsv2test_ext.egg-info/entry_points.txt
lsv2test_ext.egg-info/not-zip-safe
lsv2test_ext.egg-info/plux.json
lsv2test_ext.egg-info/requires.txt
lsv2test_ext.egg-info/top_level.txt