Metadata-Version: 2.1
Name: lsv2test-ext
Version: 2.0.0
Summary: Extensions for LocalStack
Home-page: https://github.com/localstack/localstack
Author: LocalStack Team
Author-email: info@localstack.cloud
License: Proprietary
Classifier: Programming Language :: Python :: 3
Classifier: Programming Language :: Python :: 3.10
Classifier: License :: Other/Proprietary License
Classifier: Topic :: Software Development :: Testing
Provides-Extra: runtime
Provides-Extra: test
Provides-Extra: package
